[
  {
    "name": "مخزن التقازي",
    "phone": "+218-21-123-4567",
    "email": "info@takazi-ceramics.ly",
    "address": "طرابلس، ليبيا - سوق الجمعة",
    "note": "الشركة الأم - مورد رئيسي لجميع منتجات السيراميك والبلاط"
  },
  {
    "name": "STN",
    "phone": null,
    "email": null,
    "address": null,
    "note": "مورد سيراميك"
  },
  {
    "name": "CASA TILES 108",
    "phone": null,
    "email": null,
    "address": null,
    "note": "مورد سيراميك"
  },
  {
    "name": "CASA TILES*17",
    "phone": null,
    "email": null,
    "address": null,
    "note": "مورد سيراميك"
  },
  {
    "name": "سكويمر فسيفساء",
    "phone": null,
    "email": null,
    "address": null,
    "note": "مورد فسيفساء"
  },
  {
    "name": "FAB",
    "phone": null,
    "email": null,
    "address": null,
    "note": "مورد سيراميك"
  },
  {
    "name": "SPAINCER",
    "phone": null,
    "email": null,
    "address": null,
    "note": "مورد سيراميك اسباني"
  },
  {
    "name": "علي دعفوس مصرح جمركي",
    "phone": null,
    "email": null,
    "address": null,
    "note": "مصرح جمركي"
  },
  {
    "name": "علي دعفوس/ مصرح",
    "phone": "0913218078",
    "email": null,
    "address": null,
    "note": "مصرح جمركي"
  },
  {
    "name": "أماني MBG شحن",
    "phone": null,
    "email": null,
    "address": null,
    "note": "شركة شحن"
  },
  {
    "name": "شركة صقر القولف",
    "phone": null,
    "email": null,
    "address": null,
    "note": "مورد"
  },
  {
    "name": "احواض السباحة فسيفساء",
    "phone": null,
    "email": null,
    "address": null,
    "note": "مورد فسيفساء لأحواض السباحة"
  },
  {
    "name": "HOLE FOOD",
    "phone": null,
    "email": null,
    "address": null,
    "note": "مورد"
  },
  {
    "name": "محمد المرابط شركة شحن اسبانيا",
    "phone": null,
    "email": null,
    "address": null,
    "note": "شركة شحن من اسبانيا"
  },
  {
    "name": "عماد صحاري ليبيا للشحن",
    "phone": null,
    "email": null,
    "address": null,
    "note": "شركة شحن محلية"
  },
  {
    "name": "مهند طرابلس شركة شحن",
    "phone": null,
    "email": null,
    "address": null,
    "note": "شركة شحن"
  },
  {
    "name": "OKER",
    "phone": null,
    "email": null,
    "address": null,
    "note": "مورد سيراميك"
  },
  {
    "name": "SPAINCAR (حساب يورو)",
    "phone": null,
    "email": null,
    "address": null,
    "note": null
  },
  {
    "name": "AB/00739",
    "phone": null,
    "email": null,
    "address": null,
    "note": null
  },
  {
    "name": "AB",
    "phone": null,
    "email": null,
    "address": null,
    "note": null
  },
  {
    "name": "urbana",
    "phone": null,
    "email": null,
    "address": null,
    "note": null
  },
  {
    "name": "dream",
    "phone": null,
    "email": null,
    "address": null,
    "note": null
  },
  {
    "name": "PAMESA 012659/21",
    "phone": null,
    "email": null,
    "address": null,
    "note": null
  },
  {
    "name": "pamesa 030299/21",
    "phone": null,
    "email": null,
    "address": null,
    "note": null
  },
  {
    "name": "BEYEM 430021018",
    "phone": null,
    "email": null,
    "address": null,
    "note": null
  },
  {
    "name": "pamesa 032205/21",
    "phone": null,
    "email": null,
    "address": null,
    "note": null
  },
  {
    "name": "8268/42",
    "phone": null,
    "email": null,
    "address": null,
    "note": null
  },
  {
    "name": "17838",
    "phone": null,
    "email": null,
    "address": null,
    "note": null
  },
  {
    "name": "8545/42",
    "phone": null,
    "email": null,
    "address": null,
    "note": null
  },
  {
    "name": "GRES ARAGON 1",
    "phone": null,
    "email": null,
    "address": null,
    "note": null
  },
  {
    "name": "9216/42",
    "phone": null,
    "email": null,
    "address": null,
    "note": null
  },
  {
    "name": "AB (حساب يورو)",
    "phone": null,
    "email": null,
    "address": null,
    "note": null
  },
  {
    "name": "PAMESA (حساب يورو)",
    "phone": null,
    "email": null,
    "address": null,
    "note": null
  },
  {
    "name": "BEYEM (حساب يورو)",
    "phone": null,
    "email": null,
    "address": null,
    "note": null
  },
  {
    "name": "عماد صحاري ليبيا (حساب يورو)",
    "phone": null,
    "email": null,
    "address": null,
    "note": null
  },
  {
    "name": "NOMAZUL",
    "phone": null,
    "email": null,
    "address": null,
    "note": null
  },
  {
    "name": "ECOCERAMIC (حساب يورو)",
    "phone": null,
    "email": null,
    "address": null,
    "note": null
  },
  {
    "name": "علي الهنداوي",
    "phone": null,
    "email": null,
    "address": null,
    "note": null
  },
  {
    "name": "رضاء القمودي مصرح جمركي",
    "phone": null,
    "email": null,
    "address": null,
    "note": null
  },
  {
    "name": "CIFRE (حساب يورو)",
    "phone": null,
    "email": null,
    "address": null,
    "note": null
  },
  {
    "name": "PRISSMACER (حساب يورو)",
    "phone": null,
    "email": null,
    "address": null,
    "note": null
  },
  {
    "name": "SILK ROCK (حساب يورو)",
    "phone": null,
    "email": null,
    "address": null,
    "note": null
  },
  {
    "name": "GRES ARAGON",
    "phone": null,
    "email": null,
    "address": null,
    "note": null
  },
  {
    "name": "اماني MPG",
    "phone": null,
    "email": null,
    "address": null,
    "note": null
  },
  {
    "name": "عماد صحاري ليبيا حساب دولار",
    "phone": null,
    "email": null,
    "address": null,
    "note": null
  },
  {
    "name": "العجيلي للتحويل",
    "phone": null,
    "email": null,
    "address": null,
    "note": null
  },
  {
    "name": "EME زوايا",
    "phone": null,
    "email": null,
    "address": null,
    "note": null
  },
  {
    "name": "مصرح جمركي علي الدعفوس",
    "phone": null,
    "email": null,
    "address": null,
    "note": null
  },
  {
    "name": "صالح ابو عقرب تحويل يورو",
    "phone": null,
    "email": null,
    "address": null,
    "note": null
  }
]